mcp_cli/__init__.py
mcp_cli/cli.py
mcp_cli/config.py
mcp_cli/commands/__init__.py
mcp_cli/commands/ask.py
mcp_cli/commands/servers.py
hive_mcp-0.2.0.dist-info/METADATA
hive_mcp-0.2.0.dist-info/WHEEL
hive_mcp-0.2.0.dist-info/entry_points.txt
hive_mcp-0.2.0.dist-info/top_level.txt
hive_mcp-0.2.0.dist-info/RECORD
