Metadata-Version: 2.4
Name: hive-mcp
Version: 0.2.0
Summary: A command-line interface for interacting with MCP (Model Context Protocol) servers
Author-email: Daniel Schwartz <dschwartz@trilogy.com>
License: MIT
Project-URL: Homepage, https://github.com/dschwartz-trilogy/hive-mcp
Project-URL: Bug Tracker, https://github.com/dschwartz-trilogy/hive-mcp/issues
Classifier: Programming Language :: Python :: 3
Classifier: License :: OSI Approved :: MIT License
Classifier: Operating System :: OS Independent
Requires-Python: >=3.9
Requires-Dist: mcp>=1.6.0
